{
	"source_type": "rates",
	"currency": "ves",
	"currency_symbol": "Bs.",
	"last_update": "2023-03-21",
	"data": [{
			"name": "Servicios",
			"description": null,
			"items": [{
					"name": "Servicio administrativo mínimo",
					"description": "Aplica a facturas cuyo servicio administrativo sea inferior a Bs. 210.000.000,00 / <i class='icon-info mr-0 info'></i> Bs. 210,00",
					"rates": [
						"Bs. 210.000.000,00 <br> Bs. 210,00",
						"Bs. 210.000.000,00 <br> Bs. 210,00"
					]
				},
				{
					"name": "Servicios operativos y de logística (cobro único mensual)",
					"description": "Quedan exceptuadas las facturas con servicio administrativo mínimo",
					"rates": [
						"Bs. 210.000.000,00 <br>  Bs. 210,00",
						"Bs. 210.000.000,00 <br> Bs. 210,00"
					]
				}
			]
		},
		{
			"name": "Tarjetas",
			"description": null,
			"items": [{
					"name": "Emisión (c/u)",
					"description": null,
					"rates": [
						"Bs. 45.000.000,00 <br> Bs. 45,00",
						"Bs. 45.000.000,00 <br> Bs. 45,00"
					]
				},
				{
					"name": "Reposición / Renovación (c/u)",
					"description": null,
					"rates": [
						"Bs. 45.000.000,00 <br> Bs. 45,00",
						"Bs. 45.000.000,00 <br> Bs. 45,00"
					]
				}
			]
		},
		{
			"name": "Claves",
			"description": null,
			"items": [{
				"name": "Reposición",
				"description": null,
				"rates": [
					"Bs. 35.000.000,00 <br> Bs. 35,00",
					"Bs. 35.000.000,00 <br> Bs. 35,00"
				]
			}]
		},
		{
			"name": "Cajeros automáticos*",
			"description": null,
			"items": [{
					"name": "Retiro de cajeros",
					"description": null,
					"rates": []
				},
				{
					"name": "Banco Venezolano de Crédito",
					"description": null,
					"rates": [
						null,
						"3%"
					]
				},
				{
					"name": "Otros bancos",
					"description": null,
					"rates": [
						null,
						"5%"
					]
				},
				{
					"name": "Consulta de saldo | Rechazo (fondos insuficientes o clave errada)",
					"description": null,
					"rates": []
				},
				{
					"name": "Banco Venezolano de Crédito",
					"description": null,
					"rates": [
						null,
						"Bs. 10.000,00 <br> Bs. 0,01"
					]
				},
				{
					"name": "Otros bancos",
					"description": null,
					"rates": [
						null,
						"Bs. 10.000,00 <br> Bs. 0,01"
					]
				}
			]
		},
		{
			"name": "Pagos**",
			"description": null,
			"items": [{
					"name": "Pago móvil, montos menores a Bs. 941.180.000,00 / <i class='icon-info mr-0 info'></i> Bs. 941,18",
					"description": null,
					"rates": [
						null,
						"Bs. 8.000.000,00 <br> Bs. 8,00"
					]
				},
				{
					"name": "Pago móvil, montos mayores a Bs. 941.180.000,00 / <i class='icon-info mr-0 info'></i> Bs. 941,18",
					"description": null,
					"rates": [
						null,
						"0.85%"
					]
				}
			]
		},
		{
			"name": "IVR, Centro de Contacto, App Móvil, Página Web",
			"description": null,
			"items": [{
				"name": "Consulta de saldo",
				"description": null,
				"rates": [
					0.00,
					0.00
				]
			}]
		}
	],
	"refs": [
		{
			"tag": "<i class='icon-info mr-0 info'></i>",
			"name": "Nueva expresión monetaria"
		},
		{
			"tag": "*",
			"name": "Aplican las tarifas establecidas por las instituciones bancarias."
		},
		{
			"tag": "**",
			"name": "Disponible de acuerdo con el Programa Plata Servitebca contratado."
		},
		{
			"tag": null,
			"name": "Estas tarifas podrán variar de tiempo en tiempo."
		}
	]
}
